sheets_tools/__init__.py
sheets_tools/sheets_manager.py
sheets_tools-1.0.0.dist-info/LICENSE
sheets_tools-1.0.0.dist-info/METADATA
sheets_tools-1.0.0.dist-info/WHEEL
sheets_tools-1.0.0.dist-info/top_level.txt
sheets_tools-1.0.0.dist-info/RECORD
